wake_v2/__init__.py
wake_v2/logger_collector.py
wake_v2/logger_conf.py
wake_v2/logger_interface.py
wake_v2/logger_item.py
wake_v2/logger_strategy.py
wake_v2/models.py
wake_v2/quick_logger.py
wake_v2/utils.py
warlock_waker-0.2.3.dist-info/METADATA
warlock_waker-0.2.3.dist-info/WHEEL
warlock_waker-0.2.3.dist-info/top_level.txt
warlock_waker-0.2.3.dist-info/RECORD
