Metadata-Version: 2.4
Name: warlock_waker
Version: 0.2.3
Summary: a log structure obj
Home-page: https://github.com
Author: zqyu14
Author-email: zqyu14@iflytek.com
Dynamic: author
Dynamic: author-email
Dynamic: description
Dynamic: description-content-type
Dynamic: home-page
Dynamic: summary
